odoo_fast_report_mapper/MyDumper.py
odoo_fast_report_mapper/__init__.py
odoo_fast_report_mapper/__version__.py
odoo_fast_report_mapper/eq_odoo_connection.py
odoo_fast_report_mapper/eq_report.py
odoo_fast_report_mapper/eq_utils.py
odoo_fast_report_mapper/logging_config.py
odoo_fast_report_mapper/odoo_fast_report_mapper.py
odoo_fast_report_mapper/progress.py
odoo_fast_report_mapper_equitania-0.2.5.dist-info/licenses/LICENSE.txt
odoo_report_helper/__init__.py
odoo_report_helper/exceptions.py
odoo_report_helper/odoo_connection.py
odoo_report_helper/report.py
odoo_report_helper/utils.py
odoo_fast_report_mapper_equitania-0.2.5.dist-info/METADATA
odoo_fast_report_mapper_equitania-0.2.5.dist-info/WHEEL
odoo_fast_report_mapper_equitania-0.2.5.dist-info/entry_points.txt
odoo_fast_report_mapper_equitania-0.2.5.dist-info/top_level.txt
odoo_fast_report_mapper_equitania-0.2.5.dist-info/RECORD
