Metadata-Version: 2.4
Name: odoo-fast-report-mapper-equitania
Version: 0.2.5
Summary: A Python library for creating, managing, and testing FastReport entries in Odoo environments
Home-page: https://github.com/equitania/odoo-fast-report-mapper
Author: Equitania Software GmbH
Author-email: info@equitania.de
Project-URL: Bug Reports, https://github.com/equitania/odoo-fast-report-mapper/issues
Project-URL: Source, https://github.com/equitania/odoo-fast-report-mapper
Project-URL: Documentation, https://www.ownerp.com/odoo-fastreport
Project-URL: Company, https://www.equitania.de
Keywords: odoo,fastreport,report,pdf,generator,yaml,mapping,cli
Classifier: Development Status :: 4 - Beta
Classifier: Intended Audience :: Developers
Classifier: Topic :: Software Development :: Libraries :: Python Modules
Classifier: Topic :: Office/Business
Classifier: Programming Language :: Python :: 3
Classifier: Programming Language :: Python :: 3.8
Classifier: Programming Language :: Python :: 3.9
Classifier: Programming Language :: Python :: 3.10
Classifier: Programming Language :: Python :: 3.11
Classifier: Programming Language :: Python :: 3.12
Classifier: License :: OSI Approved :: GNU Affero General Public License v3
Classifier: Operating System :: OS Independent
Classifier: Environment :: Console
Classifier: Natural Language :: English
Classifier: Natural Language :: German
Requires-Python: >=3.8
License-File: LICENSE.txt
Requires-Dist: OdooRPC>=0.10.1
Requires-Dist: click>=8.1.3
Requires-Dist: PyYaml>=5.4.1
Requires-Dist: tqdm>=4.65.0
Requires-Dist: python-dotenv>=0.19.0
Provides-Extra: dev
Requires-Dist: pytest>=6.0; extra == "dev"
Requires-Dist: pytest-cov>=2.0; extra == "dev"
Requires-Dist: black>=22.0; extra == "dev"
Requires-Dist: flake8>=4.0; extra == "dev"
Requires-Dist: mypy>=0.910; extra == "dev"
Requires-Dist: twine>=4.0; extra == "dev"
Provides-Extra: test
Requires-Dist: pytest>=6.0; extra == "test"
Requires-Dist: pytest-cov>=2.0; extra == "test"
Dynamic: author
Dynamic: author-email
Dynamic: classifier
Dynamic: description
Dynamic: description-content-type
Dynamic: home-page
Dynamic: keywords
Dynamic: license-file
Dynamic: project-url
Dynamic: provides-extra
Dynamic: requires-dist
Dynamic: requires-python
Dynamic: summary
